LICENSE
MANIFEST.in
README.md
setup.py
pytest_typhoon_config.egg-info/PKG-INFO
pytest_typhoon_config.egg-info/SOURCES.txt
pytest_typhoon_config.egg-info/dependency_links.txt
pytest_typhoon_config.egg-info/entry_points.txt
pytest_typhoon_config.egg-info/requires.txt
pytest_typhoon_config.egg-info/top_level.txt
tytest/config/__init__.py
tytest/config/exceptions.py
tytest/config/plugin.py
tytest/config/runtime_settings.py