Metadata-Version: 2.1
Name: pytest-typhoon-config
Version: 1.0.0
Summary: A Typhoon HIL plugin that facilitates test parameter configuration at runtime
Home-page: https://github.com/typhoon-hil/pytest-typhoon-config
Author: Branko Milosavljevic
Author-email: branko@typhoon-hil.com
Maintainer: Branko Milosavljevic
Maintainer-email: branko@typhoon-hil.com
License: MIT
Platform: UNKNOWN
Classifier: Development Status :: 5 - Production/Stable
Classifier: Framework :: Pytest
Classifier: Intended Audience :: Developers
Classifier: Topic :: Software Development :: Testing
Classifier: Programming Language :: Python
Classifier: Programming Language :: Python :: 3
Classifier: Programming Language :: Python :: 3.6
Classifier: Programming Language :: Python :: 3.7
Classifier: Programming Language :: Python :: 3.8
Classifier: Programming Language :: Python :: 3.9
Classifier: Programming Language :: Python :: 3.10
Classifier: Programming Language :: Python :: Implementation :: CPython
Classifier: Operating System :: OS Independent
Classifier: License :: OSI Approved :: MIT License
Requires-Python: >=3.6
License-File: LICENSE
